wodcraft/__init__.py
wodcraft/cli.py
wodcraft/core.py
wodcraft/sdk.py
wodcraft/catalog/builder.py
wodcraft-0.3.2.dist-info/licenses/LICENSE
wodcraft-0.3.2.dist-info/licenses/LICENSE-docs
wodcraft-0.3.2.dist-info/METADATA
wodcraft-0.3.2.dist-info/WHEEL
wodcraft-0.3.2.dist-info/entry_points.txt
wodcraft-0.3.2.dist-info/top_level.txt
wodcraft-0.3.2.dist-info/RECORD
