Metadata-Version: 2.4
Name: wodcraft
Version: 0.3.2
Summary: Write, lint, and compile CrossFit workouts (WODs) with a simple language and CLI. Export JSON/ICS, build a movements catalog, and get a quick timeline.
Author: WODCraft Authors
License:                                  Apache License
Project-URL: Homepage, https://github.com/Nicolas78240/WODCraft
Project-URL: Repository, https://github.com/Nicolas78240/WODCraft
Project-URL: Issues, https://github.com/Nicolas78240/WODCraft/issues
Keywords: crossfit,dsl,wod,fitness,parser,lark
Classifier: Programming Language :: Python :: 3
Classifier: Programming Language :: Python :: 3 :: Only
Classifier: License :: OSI Approved :: Apache Software License
Classifier: Operating System :: OS Independent
Classifier: Topic :: Text Processing :: Linguistic
Classifier: Topic :: Software Development :: Compilers
Requires-Python: >=3.9
License-File: LICENSE
License-File: LICENSE-docs
Requires-Dist: lark>=1.1
Dynamic: license-file
